cg_tornado/__init__.py
cg_tornado/common/__init__.py
cg_tornado/common/base.py
cg_tornado/common/helper.py
cg_tornado/common/logic.py
cg_tornado/controllers/__init__.py
cg_tornado/controllers/attachments.py
cg_tornado/controllers/user_files.py
cg_tornado/errors/__init__.py
cg_tornado/errors/errorcodes.py
cg_tornado/errors/exceptions.py
cg_tornado/errors/httperrors.py
cg_tornado/handlers/__init__.py
cg_tornado/handlers/base_api_handler.py
cg_tornado/handlers/base_web_handler.py
cg_tornado/handlers/open_handler.py
cg_tornado/models/__init__.py
cg_tornado/models/data_models.py
cg_tornado-1.0.4.dist-info/METADATA
cg_tornado-1.0.4.dist-info/RECORD
cg_tornado-1.0.4.dist-info/WHEEL
cg_tornado-1.0.4.dist-info/top_level.txt
