Metadata-Version: 2.1
Name: cg-tornado
Version: 1.0.4
Summary: CodeGini Python Library
Home-page: https://github.com/CodeGini/lib-tornado
Author: Engr Munib
Author-email: munib@codegini.com
License: MIT
Platform: UNKNOWN
